[{"image":"\/images\/tile_21.png","x":0,"y":15},{"image":"\/images\/tile_12.png","x":1,"y":13},{"image":"\/images\/tile_12.png","x":1,"y":14},{"image":"\/images\/tile_28.png","x":1,"y":15},{"image":"\/images\/tile_34.png","x":1,"y":16},{"image":"\/images\/tile_31.png","x":1,"y":17},{"image":"\/images\/tile_21.png","x":2,"y":3},{"image":"\/images\/tile_12.png","x":2,"y":13},{"image":"\/images\/tile_12.png","x":2,"y":14},{"image":"\/images\/tile_28.png","x":2,"y":15},{"image":"\/images\/tile_30.png","x":2,"y":16},{"image":"\/images\/tile_31.png","x":2,"y":17},{"image":"\/images\/tile_17.png","x":3,"y":2},{"image":"\/images\/tile_28.png","x":3,"y":3},{"image":"\/images\/tile_36.png","x":3,"y":4},{"image":"\/images\/tile_38.png","x":3,"y":5},{"image":"\/images\/tile_38.png","x":3,"y":6},{"image":"\/images\/tile_38.png","x":3,"y":7},{"image":"\/images\/tile_38.png","x":3,"y":8},{"image":"\/images\/tile_38.png","x":3,"y":9},{"image":"\/images\/tile_44.png","x":3,"y":10},{"image":"\/images\/tile_21.png","x":3,"y":13},{"image":"\/images\/tile_28.png","x":3,"y":15},{"image":"\/images\/tile_31.png","x":3,"y":16},{"image":"\/images\/tile_31.png","x":3,"y":17},{"image":"\/images\/tile_1.png","x":4,"y":0},{"image":"\/images\/tile_7.png","x":4,"y":1},{"image":"\/images\/tile_13.png","x":4,"y":2},{"image":"\/images\/tile_28.png","x":4,"y":3},{"image":"\/images\/tile_34.png","x":4,"y":4},{"image":"\/images\/tile_34.png","x":4,"y":5},{"image":"\/images\/tile_30.png","x":4,"y":6},{"image":"\/images\/tile_21.png","x":4,"y":11},{"image":"\/images\/tile_28.png","x":4,"y":13},{"image":"\/images\/tile_31.png","x":4,"y":14},{"image":"\/images\/tile_20.png","x":4,"y":15},{"image":"\/images\/tile_31.png","x":4,"y":16},{"image":"\/images\/tile_31.png","x":4,"y":17},{"image":"\/images\/tile_2.png","x":5,"y":0},{"image":"\/images\/tile_8.png","x":5,"y":1},{"image":"\/images\/tile_14.png","x":5,"y":2},{"image":"\/images\/tile_28.png","x":5,"y":3},{"image":"\/images\/tile_34.png","x":5,"y":4},{"image":"\/images\/tile_30.png","x":5,"y":5},{"image":"\/images\/tile_1.png","x":5,"y":8},{"image":"\/images\/tile_7.png","x":5,"y":9},{"image":"\/images\/tile_13.png","x":5,"y":10},{"image":"\/images\/tile_28.png","x":5,"y":11},{"image":"\/images\/tile_34.png","x":5,"y":12},{"image":"\/images\/tile_24.png","x":5,"y":13},{"image":"\/images\/tile_34.png","x":5,"y":14},{"image":"\/images\/tile_31.png","x":5,"y":15},{"image":"\/images\/tile_31.png","x":5,"y":16},{"image":"\/images\/tile_31.png","x":5,"y":17},{"image":"\/images\/tile_28.png","x":6,"y":3},{"image":"\/images\/tile_30.png","x":6,"y":4},{"image":"\/images\/tile_2.png","x":6,"y":8},{"image":"\/images\/tile_8.png","x":6,"y":9},{"image":"\/images\/tile_14.png","x":6,"y":10},{"image":"\/images\/tile_28.png","x":6,"y":11},{"image":"\/images\/tile_34.png","x":6,"y":12},{"image":"\/images\/tile_34.png","x":6,"y":13},{"image":"\/images\/tile_34.png","x":6,"y":14},{"image":"\/images\/tile_34.png","x":6,"y":15},{"image":"\/images\/tile_31.png","x":6,"y":16},{"image":"\/images\/tile_31.png","x":6,"y":17},{"image":"\/images\/tile_22.png","x":7,"y":3},{"image":"\/images\/tile_12.png","x":7,"y":8},{"image":"\/images\/tile_28.png","x":7,"y":11},{"image":"\/images\/tile_34.png","x":7,"y":12},{"image":"\/images\/tile_34.png","x":7,"y":13},{"image":"\/images\/tile_34.png","x":7,"y":14},{"image":"\/images\/tile_23.png","x":7,"y":15},{"image":"\/images\/tile_34.png","x":7,"y":16},{"image":"\/images\/tile_31.png","x":7,"y":17},{"image":"\/images\/tile_22.png","x":8,"y":11},{"image":"\/images\/tile_3.png","x":8,"y":12},{"image":"\/images\/tile_9.png","x":8,"y":13},{"image":"\/images\/tile_15.png","x":8,"y":14},{"image":"\/images\/tile_28.png","x":8,"y":15},{"image":"\/images\/tile_34.png","x":8,"y":16},{"image":"\/images\/tile_31.png","x":8,"y":17},{"image":"\/images\/tile_12.png","x":9,"y":4},{"image":"\/images\/tile_21.png","x":9,"y":8},{"image":"\/images\/tile_12.png","x":9,"y":11},{"image":"\/images\/tile_4.png","x":9,"y":12},{"image":"\/images\/tile_10.png","x":9,"y":13},{"image":"\/images\/tile_16.png","x":9,"y":14},{"image":"\/images\/tile_28.png","x":9,"y":15},{"image":"\/images\/tile_34.png","x":9,"y":16},{"image":"\/images\/tile_34.png","x":9,"y":17},{"image":"\/images\/tile_25.png","x":10,"y":8},{"image":"\/images\/tile_31.png","x":10,"y":9},{"image":"\/images\/tile_27.png","x":10,"y":10},{"image":"\/images\/tile_28.png","x":10,"y":15},{"image":"\/images\/tile_34.png","x":10,"y":16},{"image":"\/images\/tile_34.png","x":10,"y":17},{"image":"\/images\/tile_25.png","x":11,"y":8},{"image":"\/images\/tile_31.png","x":11,"y":9},{"image":"\/images\/tile_27.png","x":11,"y":10},{"image":"\/images\/tile_28.png","x":11,"y":15},{"image":"\/images\/tile_34.png","x":11,"y":16},{"image":"\/images\/tile_31.png","x":11,"y":17},{"image":"\/images\/tile_25.png","x":12,"y":8},{"image":"\/images\/tile_31.png","x":12,"y":9},{"image":"\/images\/tile_31.png","x":12,"y":10},{"image":"\/images\/tile_27.png","x":12,"y":11},{"image":"\/images\/tile_22.png","x":12,"y":15},{"image":"\/images\/tile_46.png","x":13,"y":8},{"image":"\/images\/tile_31.png","x":13,"y":9},{"image":"\/images\/tile_31.png","x":13,"y":10},{"image":"\/images\/tile_31.png","x":13,"y":11},{"image":"\/images\/tile_27.png","x":13,"y":12},{"image":"\/images\/tile_12.png","x":13,"y":14},{"image":"\/images\/tile_21.png","x":13,"y":15},{"image":"\/images\/tile_47.png","x":14,"y":8},{"image":"\/images\/tile_31.png","x":14,"y":9},{"image":"\/images\/tile_31.png","x":14,"y":10},{"image":"\/images\/tile_31.png","x":14,"y":11},{"image":"\/images\/tile_27.png","x":14,"y":12},{"image":"\/images\/tile_28.png","x":14,"y":15},{"image":"\/images\/tile_31.png","x":14,"y":16},{"image":"\/images\/tile_31.png","x":14,"y":17},{"image":"\/images\/tile_47.png","x":15,"y":8},{"image":"\/images\/tile_31.png","x":15,"y":9},{"image":"\/images\/tile_31.png","x":15,"y":10},{"image":"\/images\/tile_31.png","x":15,"y":11},{"image":"\/images\/tile_27.png","x":15,"y":12},{"image":"\/images\/tile_28.png","x":15,"y":15},{"image":"\/images\/tile_34.png","x":15,"y":16},{"image":"\/images\/tile_31.png","x":15,"y":17},{"image":"\/images\/tile_47.png","x":16,"y":8},{"image":"\/images\/tile_31.png","x":16,"y":9},{"image":"\/images\/tile_31.png","x":16,"y":10},{"image":"\/images\/tile_27.png","x":16,"y":11},{"image":"\/images\/tile_28.png","x":16,"y":15},{"image":"\/images\/tile_34.png","x":16,"y":16},{"image":"\/images\/tile_31.png","x":16,"y":17},{"image":"\/images\/tile_47.png","x":17,"y":8},{"image":"\/images\/tile_31.png","x":17,"y":9},{"image":"\/images\/tile_31.png","x":17,"y":10},{"image":"\/images\/tile_27.png","x":17,"y":11},{"image":"\/images\/tile_40.png","x":17,"y":15},{"image":"\/images\/tile_34.png","x":17,"y":16},{"image":"\/images\/tile_31.png","x":17,"y":17},{"image":"\/images\/tile_48.png","x":18,"y":8},{"image":"\/images\/tile_31.png","x":18,"y":9},{"image":"\/images\/tile_31.png","x":18,"y":10},{"image":"\/images\/tile_27.png","x":18,"y":11},{"image":"\/images\/tile_42.png","x":18,"y":15},{"image":"\/images\/tile_34.png","x":18,"y":16},{"image":"\/images\/tile_31.png","x":18,"y":17},{"image":"\/images\/tile_25.png","x":19,"y":8},{"image":"\/images\/tile_31.png","x":19,"y":9},{"image":"\/images\/tile_33.png","x":19,"y":10},{"image":"\/images\/tile_38.png","x":19,"y":11},{"image":"\/images\/tile_38.png","x":19,"y":12},{"image":"\/images\/tile_38.png","x":19,"y":13},{"image":"\/images\/tile_44.png","x":19,"y":14},{"image":"\/images\/tile_28.png","x":19,"y":15},{"image":"\/images\/tile_31.png","x":19,"y":16},{"image":"\/images\/tile_31.png","x":19,"y":17},{"image":"\/images\/tile_21.png","x":20,"y":7},{"image":"\/images\/tile_25.png","x":20,"y":8},{"image":"\/images\/tile_31.png","x":20,"y":9},{"image":"\/images\/tile_27.png","x":20,"y":10},{"image":"\/images\/tile_28.png","x":20,"y":15},{"image":"\/images\/tile_31.png","x":20,"y":16},{"image":"\/images\/tile_31.png","x":20,"y":17},{"image":"\/images\/tile_25.png","x":21,"y":7},{"image":"\/images\/tile_31.png","x":21,"y":8},{"image":"\/images\/tile_27.png","x":21,"y":9},{"image":"\/images\/tile_1.png","x":21,"y":11},{"image":"\/images\/tile_7.png","x":21,"y":12},{"image":"\/images\/tile_13.png","x":21,"y":13},{"image":"\/images\/tile_28.png","x":21,"y":14},{"image":"\/images\/tile_24.png","x":21,"y":15},{"image":"\/images\/tile_31.png","x":21,"y":16},{"image":"\/images\/tile_31.png","x":21,"y":17},{"image":"\/images\/tile_28.png","x":22,"y":7},{"image":"\/images\/tile_31.png","x":22,"y":8},{"image":"\/images\/tile_27.png","x":22,"y":9},{"image":"\/images\/tile_2.png","x":22,"y":11},{"image":"\/images\/tile_8.png","x":22,"y":12},{"image":"\/images\/tile_14.png","x":22,"y":13},{"image":"\/images\/tile_28.png","x":22,"y":14},{"image":"\/images\/tile_34.png","x":22,"y":15},{"image":"\/images\/tile_31.png","x":22,"y":16},{"image":"\/images\/tile_31.png","x":22,"y":17},{"image":"\/images\/tile_21.png","x":23,"y":6},{"image":"\/images\/tile_28.png","x":23,"y":7},{"image":"\/images\/tile_34.png","x":23,"y":8},{"image":"\/images\/tile_27.png","x":23,"y":9},{"image":"\/images\/tile_12.png","x":23,"y":12},{"image":"\/images\/tile_28.png","x":23,"y":14},{"image":"\/images\/tile_34.png","x":23,"y":15},{"image":"\/images\/tile_31.png","x":23,"y":16},{"image":"\/images\/tile_31.png","x":23,"y":17},{"image":"\/images\/tile_3.png","x":24,"y":3},{"image":"\/images\/tile_9.png","x":24,"y":4},{"image":"\/images\/tile_15.png","x":24,"y":5},{"image":"\/images\/tile_28.png","x":24,"y":6},{"image":"\/images\/tile_24.png","x":24,"y":7},{"image":"\/images\/tile_34.png","x":24,"y":8},{"image":"\/images\/tile_27.png","x":24,"y":9},{"image":"\/images\/tile_28.png","x":24,"y":13},{"image":"\/images\/tile_24.png","x":24,"y":14},{"image":"\/images\/tile_34.png","x":24,"y":15},{"image":"\/images\/tile_31.png","x":24,"y":16},{"image":"\/images\/tile_31.png","x":24,"y":17},{"image":"\/images\/tile_4.png","x":25,"y":3},{"image":"\/images\/tile_10.png","x":25,"y":4},{"image":"\/images\/tile_16.png","x":25,"y":5},{"image":"\/images\/tile_28.png","x":25,"y":6},{"image":"\/images\/tile_34.png","x":25,"y":7},{"image":"\/images\/tile_31.png","x":25,"y":8},{"image":"\/images\/tile_27.png","x":25,"y":9},{"image":"\/images\/tile_28.png","x":25,"y":13},{"image":"\/images\/tile_34.png","x":25,"y":14},{"image":"\/images\/tile_34.png","x":25,"y":15},{"image":"\/images\/tile_31.png","x":25,"y":16},{"image":"\/images\/tile_31.png","x":25,"y":17},{"image":"\/images\/tile_21.png","x":26,"y":5},{"image":"\/images\/tile_28.png","x":26,"y":6},{"image":"\/images\/tile_34.png","x":26,"y":7},{"image":"\/images\/tile_33.png","x":26,"y":8},{"image":"\/images\/tile_38.png","x":26,"y":9},{"image":"\/images\/tile_38.png","x":26,"y":10},{"image":"\/images\/tile_44.png","x":26,"y":11},{"image":"\/images\/tile_28.png","x":26,"y":13},{"image":"\/images\/tile_34.png","x":26,"y":14},{"image":"\/images\/tile_34.png","x":26,"y":15},{"image":"\/images\/tile_34.png","x":26,"y":16},{"image":"\/images\/tile_31.png","x":26,"y":17},{"image":"\/images\/tile_28.png","x":27,"y":5},{"image":"\/images\/tile_24.png","x":27,"y":6},{"image":"\/images\/tile_31.png","x":27,"y":7},{"image":"\/images\/tile_27.png","x":27,"y":8},{"image":"\/images\/tile_46.png","x":27,"y":13},{"image":"\/images\/tile_34.png","x":27,"y":14},{"image":"\/images\/tile_34.png","x":27,"y":15},{"image":"\/images\/tile_34.png","x":27,"y":16},{"image":"\/images\/tile_31.png","x":27,"y":17},{"image":"\/images\/tile_28.png","x":28,"y":5},{"image":"\/images\/tile_34.png","x":28,"y":6},{"image":"\/images\/tile_31.png","x":28,"y":7},{"image":"\/images\/tile_27.png","x":28,"y":8},{"image":"\/images\/tile_12.png","x":28,"y":12},{"image":"\/images\/tile_48.png","x":28,"y":13},{"image":"\/images\/tile_34.png","x":28,"y":14},{"image":"\/images\/tile_34.png","x":28,"y":15},{"image":"\/images\/tile_34.png","x":28,"y":16},{"image":"\/images\/tile_31.png","x":28,"y":17},{"image":"\/images\/tile_28.png","x":29,"y":5},{"image":"\/images\/tile_34.png","x":29,"y":6},{"image":"\/images\/tile_31.png","x":29,"y":7},{"image":"\/images\/tile_27.png","x":29,"y":8},{"image":"\/images\/tile_28.png","x":29,"y":13},{"image":"\/images\/tile_34.png","x":29,"y":14},{"image":"\/images\/tile_34.png","x":29,"y":15},{"image":"\/images\/tile_31.png","x":29,"y":16},{"image":"\/images\/tile_31.png","x":29,"y":17},{"image":"\/images\/tile_28.png","x":30,"y":5},{"image":"\/images\/tile_23.png","x":30,"y":6},{"image":"\/images\/tile_34.png","x":30,"y":7},{"image":"\/images\/tile_31.png","x":30,"y":8},{"image":"\/images\/tile_27.png","x":30,"y":9},{"image":"\/images\/tile_18.png","x":30,"y":12},{"image":"\/images\/tile_28.png","x":30,"y":13},{"image":"\/images\/tile_34.png","x":30,"y":14},{"image":"\/images\/tile_34.png","x":30,"y":15},{"image":"\/images\/tile_31.png","x":30,"y":16},{"image":"\/images\/tile_31.png","x":30,"y":17},{"image":"\/images\/tile_22.png","x":31,"y":5},{"image":"\/images\/tile_28.png","x":31,"y":6},{"image":"\/images\/tile_34.png","x":31,"y":7},{"image":"\/images\/tile_31.png","x":31,"y":8},{"image":"\/images\/tile_31.png","x":31,"y":9},{"image":"\/images\/tile_31.png","x":31,"y":10},{"image":"\/images\/tile_31.png","x":31,"y":11},{"image":"\/images\/tile_31.png","x":31,"y":12},{"image":"\/images\/tile_31.png","x":31,"y":13},{"image":"\/images\/tile_31.png","x":31,"y":14},{"image":"\/images\/tile_31.png","x":31,"y":15},{"image":"\/images\/tile_31.png","x":31,"y":16},{"image":"\/images\/tile_31.png","x":31,"y":17}]